{
  "categories": ["종류"],
  "quizzes": [    
    {
      "id": 1,
      "category": "종류",
      "question": "'다붓이'의 뜻으로 알맞은 것은?",
      "choices": ["벅찬 일을 견디어 낼 만큼 굳세고 야무지게", "붙어 있는 정도가 매우 가깝게", "홀가분하면서 아늑하고 정답게", "시간이나 길이가 아주 짧게"],
      "correct": 2
    },
    {
      "id": 2,
      "category": "종류",
      "question": "만나도 모르는 체하며 냉정하게 대하는 모양",
      "choices": ["야른야른", "흐리무레", "내광쓰광", "또록또록"],
      "correct": 3
    },
    {
      "id": 3,
      "category": "종류",
      "question": "'된비알'의 뜻으로 알맞은 것은?",
      "choices": ["길흉화복을 예언하여 적은 기록", "깊이 감추어진 내막의 비밀", "몹시 험한 비탈", "깎아 세운 듯한 돌의 언덕"],
      "correct": 3
    },
    {
      "id": 4,
      "category": "종류",
      "question": "'무드러기'의 뜻으로 알맞은 것은?",
      "choices": ["쓰고 남은 자질구레한 조각", "골라내거나 잘라 내고 남은 나머지", "과일의 크기가 다른 것에 비해 굵고 큰 것", "미처 다 타지 않고 남아 있는 장작개비"],
      "correct": 4
    },
    {
      "id": 5,
      "category": "종류",
      "question": "스스로 자기 자신을 망치는 일",
      "choices": ["새잡이", "제잡이", "말잡이", "채잡이"],
      "correct": 2
    }
  ]
}